ssb_parquedit/__init__.py
ssb_parquedit/__main__.py
ssb_parquedit/functions.py
ssb_parquedit/py.typed
ssb_parquedit-0.0.1.dist-info/METADATA
ssb_parquedit-0.0.1.dist-info/WHEEL
ssb_parquedit-0.0.1.dist-info/entry_points.txt
ssb_parquedit-0.0.1.dist-info/licenses/LICENSE
ssb_parquedit-0.0.1.dist-info/RECORD
