Metadata-Version: 2.4
Name: ssb-parquedit
Version: 0.0.1
Summary: SSB Parquedit
License-Expression: MIT
License-File: LICENSE
Author: Team Fellesfunksjoner
Author-email: osn@ssb.no
Maintainer: Statistics Norway, Data enablement Department (724)
Requires-Python: >=3.10,<4.0
Classifier: Development Status :: 4 - Beta
Classifier: Programming Language :: Python :: 3
Classifier: Programming Language :: Python :: 3.10
Classifier: Programming Language :: Python :: 3.11
Classifier: Programming Language :: Python :: 3.12
Classifier: Programming Language :: Python :: 3.13
Classifier: Programming Language :: Python :: 3.14
Requires-Dist: click (>=8.0.1)
Project-URL: Changelog, https://github.com/statisticsnorway/ssb-parquedit/releases
Project-URL: Documentation, https://statisticsnorway.github.io/ssb-parquedit
Project-URL: Homepage, https://github.com/statisticsnorway/ssb-parquedit
Project-URL: Repository, https://github.com/statisticsnorway/ssb-parquedit
